Metadata-Version: 2.4
Name: llama-index-tools-exa
Version: 0.4.1
Summary: llama-index tools exa integration
Author-email: Your Name <you@example.com>
Maintainer: jeffzwang
License-Expression: MIT
License-File: LICENSE
Requires-Python: <4.0,>=3.9
Requires-Dist: exa-py<2,>=1.0.8
Requires-Dist: llama-index-core<0.15,>=0.13.0
